setup.py
Flask_Should_DSL.egg-info/PKG-INFO
Flask_Should_DSL.egg-info/SOURCES.txt
Flask_Should_DSL.egg-info/dependency_links.txt
Flask_Should_DSL.egg-info/not-zip-safe
Flask_Should_DSL.egg-info/requires.txt
Flask_Should_DSL.egg-info/top_level.txt
flask_should_dsl/__init__.py
flask_should_dsl/matchers.py