Metadata-Version: 1.0
Name: Flask-Should-DSL
Version: 0.4
Summary: A flask extension for testing with should-dsl
Home-page: http://obmarg.github.com/flask-should-dsl/
Author: Graeme Coupar
Author-email: grambo@grambo.me.uk
License: BSD
Platform: any
Classifier: Environment :: Web Environment
Classifier: Intended Audience :: Developers
Classifier: License :: OSI Approved :: BSD License
Classifier: Operating System :: OS Independent
Classifier: Programming Language :: Python
Classifier: Topic :: Internet :: WWW/HTTP :: Dynamic Content
Classifier: Topic :: Software Development :: Libraries :: Python Modules
Classifier: Topic :: Software Development :: Testing
